kahi_post_person_work_cleaning/Kahi_post_person_work_cleaning.py
kahi_post_person_work_cleaning/__init__.py
kahi_post_person_work_cleaning/_version.py
Kahi_post_person_work_cleaning-0.1.0.dist-info/LICENSE
Kahi_post_person_work_cleaning-0.1.0.dist-info/METADATA
Kahi_post_person_work_cleaning-0.1.0.dist-info/WHEEL
Kahi_post_person_work_cleaning-0.1.0.dist-info/top_level.txt
Kahi_post_person_work_cleaning-0.1.0.dist-info/RECORD
