Metadata-Version: 2.2
Name: Kahi_post_person_work_cleaning
Version: 0.1.0
Summary: Kahi plugin for post processing work cleaning for person.
Home-page: https://github.com/colav/Kahi_plugins
Author: Colav
Author-email: colav@udea.edu.co
License: BSD
License-File: LICENSE
Requires-Dist: kahi
Dynamic: author
Dynamic: author-email
Dynamic: description
Dynamic: description-content-type
Dynamic: home-page
Dynamic: license
Dynamic: requires-dist
Dynamic: summary
